rsactftool/RsaCtfTool.py
rsactftool/__init__.py
rsactftool/attacks/__init__.py
rsactftool/attacks/multi_keys/__init__.py
rsactftool/attacks/multi_keys/commonfactors.py
rsactftool/attacks/multi_keys/hastads.py
rsactftool/attacks/multi_keys/same_n_huge_e.py
rsactftool/attacks/single_key/__init__.py
rsactftool/attacks/single_key/binary_polinomial_factoring.py
rsactftool/attacks/single_key/boneh_durfee.py
rsactftool/attacks/single_key/comfact_cn.py
rsactftool/attacks/single_key/cube_root.py
rsactftool/attacks/single_key/ecm.py
rsactftool/attacks/single_key/ecm2.py
rsactftool/attacks/single_key/euler.py
rsactftool/attacks/single_key/factordb.py
rsactftool/attacks/single_key/fermat.py
rsactftool/attacks/single_key/londahl.py
rsactftool/attacks/single_key/mersenne_primes.py
rsactftool/attacks/single_key/noveltyprimes.py
rsactftool/attacks/single_key/nullattack.py
rsactftool/attacks/single_key/partial_q.py
rsactftool/attacks/single_key/pastctfprimes.py
rsactftool/attacks/single_key/pollard_p_1.py
rsactftool/attacks/single_key/pollard_rho.py
rsactftool/attacks/single_key/qicheng.py
rsactftool/attacks/single_key/roca.py
rsactftool/attacks/single_key/siqs.py
rsactftool/attacks/single_key/smallfraction.py
rsactftool/attacks/single_key/smallq.py
rsactftool/attacks/single_key/wiener.py
rsactftool/attacks/single_key/yafu
rsactftool/lib/__init__.py
rsactftool/lib/customlogger.py
rsactftool/lib/exceptions.py
rsactftool/lib/keys_wrapper.py
rsactftool/lib/rsa_attack.py
rsactftool/lib/rsalibnum.py
rsactftool/lib/timeout.py
rsactftool/lib/utils.py
rsactftool/sage/binary_polinomial_factoring.sage
rsactftool/sage/boneh_durfee.sage
rsactftool/sage/ecm.sage
rsactftool/sage/ecm2.sage
rsactftool/sage/qicheng.sage
rsactftool/sage/roca_attack.py
rsactftool/sage/sage_functions.py
rsactftool/sage/smallfraction.sage
rsactftool-1.1.dist-info/entry_points.txt
rsactftool-1.1.dist-info/LICENSE.md
rsactftool-1.1.dist-info/WHEEL
rsactftool-1.1.dist-info/METADATA
rsactftool-1.1.dist-info/RECORD
