Metadata-Version: 2.1
Name: rsactftool
Version: 1.1
Summary: RSA attack tool (mainly for ctf) - retreive private key from weak public key and/or uncipher data
Home-page: https://github.com/borari/RsaCtfTool
License: Beerware
Keywords: rsa-attack,rsa,cryptography
Author: Ganapati
Maintainer: borari
Requires-Python: >=3.8,<3.9
Classifier: License :: Other/Proprietary License
Classifier: Programming Language :: Python :: 3
Classifier: Programming Language :: Python :: 3.8
Classifier: Topic :: Scientific/Engineering :: Mathematics
Classifier: Topic :: Security :: Cryptography
Provides-Extra: sagemath
Requires-Dist: cryptography (==3.2)
Requires-Dist: gmpy (==1.17)
Requires-Dist: gmpy2 (==2.1.0b5)
Requires-Dist: pycryptodome (==3.9.7)
Requires-Dist: requests (==2.20.0)
Requires-Dist: six (==1.12.0)
Requires-Dist: sympy (==1.3)
Requires-Dist: urllib3 (==1.24.2)
Project-URL: Repository, https://github.com/borari/RsaCtfTool
